<data.SpriteMakerModel>
  <myComponents>
    <entry>
      <newengine.sprite.component.ComponentType>
        <typename>newengine.sprite.components.Images</typename>
      </newengine.sprite.component.ComponentType>
      <newengine.sprite.components.Images>
        <imageFilePath>images/characters/Lava.jpg</imageFilePath>
      </newengine.sprite.components.Images>
    </entry>
  </myComponents>
  <myScriptMap/>
  <actualComponents>
    <newengine.sprite.components.Images reference="../../myComponents/entry/newengine.sprite.components.Images"/>
  </actualComponents>
  <skills/>
</data.SpriteMakerModel>