<data.SpriteMakerModel>
  <myComponents class="com.sun.javafx.collections.ObservableMapWrapper">
    <values>
      <outer-class reference="../.."/>
    </values>
    <backingMap>
      <entry>
        <newengine.sprite.component.ComponentType>
          <typename>newengine.sprite.components.Position</typename>
        </newengine.sprite.component.ComponentType>
        <newengine.sprite.components.Position>
          <pos>
            <x>0.06142857142857143</x>
            <y>0.05</y>
          </pos>
          <heading>0.0</heading>
          <isMoving>false</isMoving>
          <followingSprite>false</followingSprite>
        </newengine.sprite.components.Position>
      </entry>
      <entry>
        <newengine.sprite.component.ComponentType>
          <typename>newengine.sprite.components.PathFollower</typename>
        </newengine.sprite.component.ComponentType>
        <newengine.sprite.components.PathFollower>
          <path>
            <myPath class="linked-list">
              <commons.point.GamePoint reference="../../../../../entry/newengine.sprite.components.Position/pos"/>
              <commons.point.GamePoint>
                <x>0.18428571428571427</x>
                <y>0.05</y>
              </commons.point.GamePoint>
              <commons.point.GamePoint>
                <x>0.30714285714285716</x>
                <y>0.05</y>
              </commons.point.GamePoint>
              <commons.point.GamePoint>
                <x>0.43</x>
                <y>0.05</y>
              </commons.point.GamePoint>
              <commons.point.GamePoint>
                <x>0.5528571428571428</x>
                <y>0.05</y>
              </commons.point.GamePoint>
              <commons.point.GamePoint>
                <x>0.6757142857142857</x>
                <y>0.05</y>
              </commons.point.GamePoint>
              <commons.point.GamePoint>
                <x>0.7985714285714286</x>
                <y>0.05</y>
              </commons.point.GamePoint>
              <commons.point.GamePoint>
                <x>0.9214285714285714</x>
                <y>0.05</y>
              </commons.point.GamePoint>
            </myPath>
            <pathName>TestPath</pathName>
          </path>
          <speed>0.0</speed>
        </newengine.sprite.components.PathFollower>
      </entry>
    </backingMap>
  </myComponents>
  <myScriptMap class="com.sun.javafx.collections.ObservableMapWrapper">
    <backingMap/>
  </myScriptMap>
  <actualComponents>
    <newengine.sprite.components.PathFollower reference="../../myComponents/backingMap/entry[2]/newengine.sprite.components.PathFollower"/>
    <newengine.sprite.components.Position reference="../../myComponents/backingMap/entry/newengine.sprite.components.Position"/>
  </actualComponents>
  <skills/>
</data.SpriteMakerModel>